[
    {
        "title": "Aluroni",
        "description": "Aluroni é um projeto que desenvolvi para criar uma página de cardápio interativa. Onde os usuários podem filtrar e ordenar as opções para visualizar as refeições disponíveis.",
        "linkGit":"https://github.com/xJuniorFx/Aluroni",
        "linkProject":"https://xjuniorfx.github.io/Aluroni/",
        "imgLink": "assets/img/Aluroni.png"
    },
    {
        "title": "Alura Studies",
        "description": "Com Alura Studies, é um projeto que proporciona um controle visual claro das suas atividades e poderá gerenciar seu tempo de maneira mais eficaz.",
        "linkGit":"https://github.com/xJuniorFx?tab=repositories",
        "linkProject":"https://xjuniorfx.github.io/AluraStudies/",
        "imgLink": "assets/img/aluraStudies.png"
    },
    {
        "title": "Maintenance",
        "description": "Update coming soon",
        "linkGit":"https://github.com/xJuniorFx?tab=repositories",
        "linkProject":"#projects",
        "imgLink": "assets/img/maintenance.png"
    }
]